pykmer/__init__.py
pykmer/basics.py
pykmer/bits.py
pykmer/codec16.py
pykmer/codec8.py
pykmer/container.py
pykmer/dist.py
pykmer/exceptions.py
pykmer/exset.py
pykmer/file.py
pykmer/kfset.py
pykmer/kset.py
pykmer/misc.py
pykmer/sort.py
pykmer/sparse.py
pykmer/stats.py
pykmer/uf.py
pykmer-0.1.dist-info/DESCRIPTION.rst
pykmer-0.1.dist-info/METADATA
pykmer-0.1.dist-info/RECORD
pykmer-0.1.dist-info/WHEEL
pykmer-0.1.dist-info/metadata.json
pykmer-0.1.dist-info/top_level.txt
