Metadata-Version: 2.0
Name: pykmer
Version: 0.1
Summary: A pure python k-mer sequence analysis toolkit
Home-page: http://github.com/drtconway/pykmer
Author: Tom Conway
Author-email: tconway@au1.ibm.com
License: Apache2
Keywords: bioinformatics genomics pathogenomics
Platform: UNKNOWN
Requires-Dist: docopt
